mpy3/main.py
mpy3-1.1.dist-info/LICENSE
mpy3-1.1.dist-info/METADATA
mpy3-1.1.dist-info/WHEEL
mpy3-1.1.dist-info/entry_points.txt
mpy3-1.1.dist-info/top_level.txt
mpy3-1.1.dist-info/RECORD
